[
  {
    "receivestring": "",
    "disablestring": "",
    "timeout": "16",
    "type": "gateway-icmp:gateway-icmpstate",
    "loadbalancer": "bigip.xip.se",
    "interval": "5",
    "sendstring": "",
    "name": "/Common/gateway_icmp"
  },
  {
    "receivestring": "",
    "disablestring": "",
    "timeout": "16",
    "type": "http:httpstate",
    "loadbalancer": "bigip.xip.se",
    "interval": "5",
    "sendstring": "GET /\\r\\n",
    "name": "/Common/http"
  },
  {
    "receivestring": "Server\\:",
    "disablestring": "",
    "timeout": "16",
    "type": "http:httpstate",
    "loadbalancer": "bigip.xip.se",
    "interval": "5",
    "sendstring": "HEAD / HTTP/1.0\\r\\n\\r\\n",
    "name": "/Common/http_head_f5"
  },
  {
    "receivestring": "",
    "disablestring": "",
    "timeout": "16",
    "type": "https:httpsstate",
    "loadbalancer": "bigip.xip.se",
    "interval": "5",
    "sendstring": "GET /\\r\\n",
    "name": "/Common/https"
  },
  {
    "receivestring": "",
    "disablestring": "",
    "timeout": "16",
    "type": "https:httpsstate",
    "loadbalancer": "bigip.xip.se",
    "interval": "5",
    "sendstring": "GET /\\r\\n",
    "name": "/Common/https_443"
  },
  {
    "receivestring": "Server\\:",
    "disablestring": "",
    "timeout": "16",
    "type": "https:httpsstate",
    "loadbalancer": "bigip.xip.se",
    "interval": "5",
    "sendstring": "HEAD / HTTP/1.0\\r\\n\\r\\n",
    "name": "/Common/https_head_f5"
  },
  {
    "receivestring": "",
    "disablestring": "",
    "timeout": "16",
    "type": "icmp:icmpstate",
    "loadbalancer": "bigip.xip.se",
    "interval": "5",
    "sendstring": "",
    "name": "/Common/icmp"
  },
  {
    "receivestring": "Balanced",
    "disablestring": "",
    "timeout": "16",
    "type": "https:httpsstate",
    "loadbalancer": "bigip.xip.se",
    "interval": "5",
    "sendstring": "GET / HTTP/1.1\\r\\nHost: host.domain.com\\r\\nConnection: Close\\r\\n\\r\\n",
    "name": "/Common/loadbalancing-se-https"
  },
  {
    "receivestring": "",
    "disablestring": "",
    "timeout": "16",
    "type": "real-server:real-serverstate",
    "loadbalancer": "bigip.xip.se",
    "interval": "5",
    "sendstring": "",
    "name": "/Common/real_server"
  },
  {
    "receivestring": "",
    "disablestring": "",
    "timeout": "30",
    "type": "snmp-dca:snmp-dcastate",
    "loadbalancer": "bigip.xip.se",
    "interval": "10",
    "sendstring": "",
    "name": "/Common/snmp_dca"
  },
  {
    "receivestring": "",
    "disablestring": "",
    "timeout": "16",
    "type": "tcp:tcpstate",
    "loadbalancer": "bigip.xip.se",
    "interval": "5",
    "sendstring": "",
    "name": "/Common/tcp"
  },
  {
    "receivestring": "",
    "disablestring": "",
    "timeout": "16",
    "type": "tcp-half-open:tcp-half-openstate",
    "loadbalancer": "bigip.xip.se",
    "interval": "5",
    "sendstring": "",
    "name": "/Common/tcp_half_open"
  },
  {
    "receivestring": "",
    "disablestring": "",
    "timeout": "16",
    "type": "udp:udpstate",
    "loadbalancer": "bigip.xip.se",
    "interval": "5",
    "sendstring": "default send string",
    "name": "/Common/udp"
  },
  {
    "receivestring": "HTTP/1.",
    "disablestring": "",
    "timeout": "16",
    "type": "http:httpstate",
    "loadbalancer": "bigip.xip.se",
    "interval": "5",
    "sendstring": "GET /index.html HTTP/1.1\\r\\nHost: grafana.xip.se\\r\\nConnection: Close\\r\\n\\r\\n",
    "name": "/example_NAT64/App1/grafana_http_monitor"
  },
  {
    "receivestring": "HTTP/1.",
    "disablestring": "",
    "timeout": "16",
    "type": "http:httpstate",
    "loadbalancer": "bigip.xip.se",
    "interval": "5",
    "sendstring": "GET /index.html HTTP/1.1\\r\\nHost: grafana.xip.se\\r\\nConnection: Close\\r\\n\\r\\n",
    "name": "/TEST_HTTPSMonitor/Application/mymonitor"
  }
]